getpost_fileserver/__init__.py
getpost_fileserver/app.py
getpost_fileserver/server.py
getpost_fileserver-0.1.0.dist-info/METADATA
getpost_fileserver-0.1.0.dist-info/WHEEL
getpost_fileserver-0.1.0.dist-info/entry_points.txt
getpost_fileserver-0.1.0.dist-info/top_level.txt
getpost_fileserver-0.1.0.dist-info/RECORD
